Sqlite3En/Sqlite3En.py
Sqlite3En/__init__.py
Sqlite3En-0.0.7.dist-info/METADATA
Sqlite3En-0.0.7.dist-info/WHEEL
Sqlite3En-0.0.7.dist-info/top_level.txt
Sqlite3En-0.0.7.dist-info/RECORD
