Metadata-Version: 2.1
Name: Sqlite3En
Version: 0.0.7
Summary: UNKNOWN
Home-page: https://github.com/yous1010/Sqlite3En_python/tree/master
Author: Yousof Bader Yousof
Author-email: phyous1010@gmail.com
License: UNKNOWN
Project-URL: Bug Tracker, https://github.com/yous1010/Sqlite3En_python/issues
Platform: UNKNOWN
Classifier: Programming Language :: Python :: 2.7
Classifier: License :: OSI Approved :: MIT License
Classifier: Operating System :: OS Independent
Requires-Python: >=2.7
